
 [
    {
      "id": 1,
      "image": "",
      "title": "اريد ان اذهب الى بعض الاماكن بالسيارى",
      "time": "ساعة ",
      "sex": "رجال",
      "type": "سيارة",
      "number": "2فزعو"

    },
   {
     "id": 2,
     "image": "",
     "title": "اريد ان اذهب الى لكى اعزم",
     "time": "ساعة ",
     "sex": "نساء",
     "type": "اكل",
     "number": "15فزعو"

   },
   {
     "id": 3,
     "image": "",
     "title": "اريد ان اذهب الى بعض الاماكن بالسيارة لكى اذهب بسرعة كبيرة",
     "time": "ساعة ",
     "sex": "رجال",
     "type": "سيارة",
     "number": "15فزعو"

   },
   {
     "id": 4,
     "image": "",
     "title": "اريد ان اذهب الى لكى اعزم",
     "time": "ساعة ",
     "sex": "نساء",
     "type": "اكل",
     "number": "15فزعو"

   }
     ]
